{
    "__style__": {
        "fontFamily": "@fontPrimaryFamily",
        "fontSizeMessage": "@fontPrimarySizeHeading5",
        "fontSizeDescription": "@fontPrimarySize",
        "colorMessage": "@colorTextPrimary",
        "colorDescription": "@colorTextSecondary",
        "colorBg": "@colorBgBase",
        "colorBgDark": "@colorMain-11",
        "colorBgShadow": "@colorTextBase",
        "colorClose": "@colorTextTertiary",
        "colorCloseHover": "@colorTextBase",
        "radiusBg": "@radiusPrimaryLG"
    }
}
